{
  "id": "L2NvbnRlbnQvZm9ybXMvYWYvcmFlL2R2ZS10ZXN0",
  "fieldType": "form",
  "title": "formatting-using-custom-functions",
  "action": "/adobe/forms/af/submit/L2NvbnRlbnQvZm9ybXMvYWYvcmFlL2R2ZS10ZXN0",
  "lang": "en",
  "properties": {
    "fd:dor": {
      "dorType": "none"
    },
    "fd:path": "/content/forms/af/rae/dve-test/jcr:content/guideContainer",
    "fd:schemaType": "BASIC",
    "fd:formDataEnabled": false
  },
  "columnCount": 12,
  "gridClassNames": "aem-Grid aem-Grid--12 aem-Grid--default--12",
  "columnClassNames": {
    "telephoneinput": "aem-GridColumn aem-GridColumn--default--12"
  },
  "events": {
    "custom:setProperty": [
      "$event.payload"
    ]
  },
  ":itemsOrder": [
    "telephoneinput"
  ],
  "metadata": {
    "version": "1.0.0",
    "grammar": "json-formula-1.0.0"
  },
  "adaptiveform": "0.12.5",
  ":type": "forms-components-examples/components/form/container",
  ":items": {
    "telephoneinput": {
      "id": "telephoneinput-5d60324571",
      "fieldType": "text-input",
      "name": "telephoneinput1711807711348",
      "type": "string",
      "displayValueExpression": "formatTelephoneInput($field)",
      "label": {
        "value": "Telephone Input"
      },
      "events": {
        "custom:setProperty": [
          "$event.payload"
        ]
      },
      "properties": {
        "fd:dor": {
          "dorExclusion": false
        },
        "fd:path": "/content/forms/af/rae/dve-test/jcr:content/guideContainer/telephoneinput",
        "fd:rules": {
          "validationStatus": "valid"
        }
      },
      "autocomplete": "tel",
      ":type": "forms-components-examples/components/form/telephoneinput"
    }
  }
}
